ea_psu_controller/__init__.py
ea_psu_controller/psu_ea.py
ea_psu_controller-1.1.0.data/data/99-ea-psu.rules
ea_psu_controller-1.1.0.dist-info/LICENCE
ea_psu_controller-1.1.0.dist-info/METADATA
ea_psu_controller-1.1.0.dist-info/WHEEL
ea_psu_controller-1.1.0.dist-info/top_level.txt
ea_psu_controller-1.1.0.dist-info/RECORD
