Metadata-Version: 2.1
Name: ea-psu-controller
Version: 1.1.0
Summary: Controller for Elektro-Automatik power supplies
Home-page: https://github.com/synapticon/somanet_test_suite/tree/master/psu
Author: Henrik Strötgen
Author-email: hstroetgen@synapticon.com
License: MIT
Keywords: power supply unit,psu
Platform: UNKNOWN
Classifier: Programming Language :: Python :: 3
Classifier: License :: OSI Approved :: MIT License
Classifier: Operating System :: POSIX :: Linux
Classifier: Operating System :: Microsoft :: Windows :: Windows 7
Classifier: Topic :: System :: Hardware :: Hardware Drivers
Requires-Dist: pyserial (>=3.4)
